readfish_summarise-0.2.7.dist-info/METADATA
readfish_summarise-0.2.7.dist-info/WHEEL
readfish_summarise-0.2.7.dist-info/entry_points.txt
readfish_summarise/fastq_utils.py
readfish_summarise/__init__.py
readfish_summarise/cli.py
readfish_summarise/summarise.py
readfish_summarise/readfish_summarise.cpython-38-darwin.so
readfish_summarise-0.2.7.dist-info/RECORD
