Metadata-Version: 2.3
Name: readfish_summarise
Version: 0.2.7
Classifier: Programming Language :: Rust
Classifier: Programming Language :: Python :: Implementation :: CPython
Classifier: Programming Language :: Python :: Implementation :: PyPy
Classifier: Intended Audience :: Science/Research
Classifier: Programming Language :: Python :: 3.8
Classifier: Programming Language :: Python :: 3.9
Classifier: Programming Language :: Python :: 3.10
Classifier: Programming Language :: Python :: 3.11
Requires-Dist: click
Requires-Dist: mappy
Requires-Dist: mappy-rs
Requires-Dist: pytest
Requires-Dist: alive-progress
Summary: A blazingly fast Python/Rust library for summarising readfish FASTQ output
Keywords: bioinformatics,python,rust,readfish,analysis
Author-email: Rory Munro <rory.munro@nottingham.ac.uk>
Maintainer-email: Rory Munro <rory.munro@nottingham.ac.uk>
License: BSD 3-Clause License
Requires-Python: >=3.8
Project-URL: Bug Tracker, https://github.com/Adoni5/ReadfishSummarise/issues
Project-URL: Source Code, https://github.com/Adoni5/ReadfishSummarise
